copado_ai_sdk/__init__.py
copado_ai_sdk/_version.py
copado_ai_sdk/auth.py
copado_ai_sdk/client.py
copado_ai_sdk/exceptions.py
copado_ai_sdk/types.py
copado_ai_sdk/services/__init__.py
copado_ai_sdk/services/activity.py
copado_ai_sdk/services/dialogue.py
copado_ai_sdk/services/document.py
copado_ai_sdk/services/integration.py
copado_ai_sdk/services/organization.py
copado_ai_sdk/services/workspace.py
copado_ai_sdk-0.1.0.dist-info/METADATA
copado_ai_sdk-0.1.0.dist-info/WHEEL
copado_ai_sdk-0.1.0.dist-info/RECORD
