Metadata-Version: 2.4
Name: copado_ai_sdk
Version: 0.1.0
Summary: Python SDK for Copado AI - AI-powered DevOps assistant with document analysis and knowledge integration
Author-email: Fekry Mostafa <mostafaf@copado.com>
Maintainer-email: Copado Support <success@copado.com>
License: MIT
Keywords: ai,automation,copado,devops,salesforce
Classifier: Development Status :: 4 - Beta
Classifier: Intended Audience :: Developers
Classifier: License :: OSI Approved :: MIT License
Classifier: Operating System :: OS Independent
Classifier: Programming Language :: Python :: 3
Classifier: Programming Language :: Python :: 3.9
Classifier: Programming Language :: Python :: 3.10
Classifier: Programming Language :: Python :: 3.11
Classifier: Programming Language :: Python :: 3.12
Classifier: Topic :: Software Development :: Libraries :: Python Modules
Classifier: Topic :: System :: Systems Administration
Requires-Python: >=3.9
Requires-Dist: httpx>=0.27
Requires-Dist: pydantic>=2.7
Requires-Dist: python-dotenv>=1.0
